print_dict/__init__.py
print_dict/config.py
print_dict/pprint_python_3_9.py
print_dict/print_dict.py
print_dict-0.1.19.dist-info/entry_points.txt
print_dict-0.1.19.dist-info/WHEEL
print_dict-0.1.19.dist-info/METADATA
print_dict-0.1.19.dist-info/RECORD
